dpln/__init__.py
dpln/util.py
dpln/autograd/__init__.py
dpln/autograd/function.py
dpln/autograd/random.py
dpln/autograd/tensor.py
dpln/autograd/utils.py
dpln/data/__init__.py
dpln/data/collate.py
dpln/data/dataloader.py
dpln/data/dataset.py
dpln/data/fetch.py
dpln/data/sampler.py
dpln/nn/__init__.py
dpln/nn/functional.py
dpln/nn/init.py
dpln/nn/parameter.py
dpln/nn/utils.py
dpln/nn/modules/__init__.py
dpln/nn/modules/activation.py
dpln/nn/modules/container.py
dpln/nn/modules/conv.py
dpln/nn/modules/dropout.py
dpln/nn/modules/flatten.py
dpln/nn/modules/linear.py
dpln/nn/modules/loss.py
dpln/nn/modules/module.py
dpln/nn/modules/pooling.py
dpln/optim/__init__.py
dpln/optim/adam.py
dpln/optim/hebb.py
dpln/optim/optimizer.py
dpln/optim/sgd.py
dpln-0.1.2.dist-info/LICENSE
dpln-0.1.2.dist-info/METADATA
dpln-0.1.2.dist-info/WHEEL
dpln-0.1.2.dist-info/top_level.txt
dpln-0.1.2.dist-info/RECORD
