Metadata-Version: 2.1
Name: dpln
Version: 0.1.2
Summary: A tiny library for deep learning using numpy.
Home-page: https://github.com/shizuku/dpln
Author: shizuku
Author-email: 2112165916@qq.com
License: UNKNOWN
Project-URL: Bug Tracker, https://github.com/shizuku/dpln/issues
Platform: UNKNOWN
Classifier: Programming Language :: Python :: 3
Classifier: License :: OSI Approved :: MIT License
Classifier: Operating System :: OS Independent
Requires-Python: >=3.6
License-File: LICENSE
